fleet_mcp/__init__.py
fleet_mcp/__main__.py
fleet_mcp/auth/__init__.py
fleet_mcp/auth/middleware.py
fleet_mcp/auth/models.py
fleet_mcp/auth/token_manager.py
fleet_mcp/clients/__init__.py
fleet_mcp/clients/coder_client.py
fleet_mcp/clients/exceptions.py
fleet_mcp/clients/metadata_client.py
fleet_mcp/models/__init__.py
fleet_mcp/models/agent.py
fleet_mcp/models/errors.py
fleet_mcp/models/metadata.py
fleet_mcp/models/project.py
fleet_mcp/models/remote.py
fleet_mcp/models/responses.py
fleet_mcp/models/task.py
fleet_mcp/repositories/__init__.py
fleet_mcp/repositories/agent_repository.py
fleet_mcp/repositories/metadata_repository.py
fleet_mcp/repositories/project_repository.py
fleet_mcp/repositories/task_repository.py
fleet_mcp/services/__init__.py
fleet_mcp/services/agent_service.py
fleet_mcp/services/metadata_service.py
fleet_mcp/services/project_service.py
fleet_mcp/services/task_service.py
fleet_mcp/services/taskfile_parser.py
fleet_mcp/tools/__init__.py
fleet_mcp/tools/cancel_task.py
fleet_mcp/tools/create_agent.py
fleet_mcp/tools/delete_agent.py
fleet_mcp/tools/list_agents.py
fleet_mcp/tools/list_projects.py
fleet_mcp/tools/list_roles.py
fleet_mcp/tools/restart_agent.py
fleet_mcp/tools/show_agent.py
fleet_mcp/tools/show_logs.py
fleet_mcp/tools/show_task_history.py
fleet_mcp/tools/start_task.py
setup_fleet_mcp-0.12.1.dist-info/METADATA
setup_fleet_mcp-0.12.1.dist-info/WHEEL
setup_fleet_mcp-0.12.1.dist-info/entry_points.txt
setup_fleet_mcp-0.12.1.dist-info/RECORD
