Metadata-Version: 2.4
Name: setup-fleet-mcp
Version: 0.12.1
Summary: Fleet management using MCP for AI agents in Coder workspaces
Requires-Python: >=3.10
Requires-Dist: fastmcp==2.13.0.2
Requires-Dist: httpx==0.28.1
Requires-Dist: pydantic==2.12.3
Requires-Dist: python-dotenv==1.2.1
Requires-Dist: uvicorn==0.34.0
